README.rst
setup.py
pyramid_cubicweb/__init__.py
pyramid_cubicweb/auth.py
pyramid_cubicweb/bwcompat.py
pyramid_cubicweb/core.py
pyramid_cubicweb/defaults.py
pyramid_cubicweb/init_instance.py
pyramid_cubicweb/login.py
pyramid_cubicweb/predicates.py
pyramid_cubicweb/profile.py
pyramid_cubicweb/resources.py
pyramid_cubicweb/rest_api.py
pyramid_cubicweb/session.py
pyramid_cubicweb/tools.py
pyramid_cubicweb.egg-info/PKG-INFO
pyramid_cubicweb.egg-info/SOURCES.txt
pyramid_cubicweb.egg-info/dependency_links.txt
pyramid_cubicweb.egg-info/not-zip-safe
pyramid_cubicweb.egg-info/requires.txt
pyramid_cubicweb.egg-info/top_level.txt
pyramid_cubicweb/tests/__init__.py
pyramid_cubicweb/tests/test_bw_request.py
pyramid_cubicweb/tests/test_core.py
pyramid_cubicweb/tests/test_login.py
pyramid_cubicweb/tests/test_rest_api.py
pyramid_cubicweb/tests/test_tools.py