Metadata-Version: 1.1
Name: pyramid-cubicweb
Version: 0.7.0
Summary: Integrate CubicWeb with a Pyramid application.
Home-page: https://www.cubicweb.org/project/pyramid-cubicweb
Author: Christophe de Vienne
Author-email: username: christophe, domain: unlish.com
License: UNKNOWN
Platform: UNKNOWN
Classifier: Development Status :: 3 - Alpha
Classifier: Environment :: Web Environment
Classifier: Intended Audience :: Developers
Classifier: License :: Public Domain
Classifier: Natural Language :: English
Classifier: Operating System :: OS Independent
Classifier: Programming Language :: Python
Classifier: Programming Language :: Python :: 2.7
Classifier: Programming Language :: Python :: 3
Classifier: Framework :: Pylons
Classifier: Topic :: Internet :: WWW/HTTP
Classifier: Topic :: Internet :: WWW/HTTP :: WSGI
Classifier: Topic :: Software Development :: Libraries :: Python Modules
